[
  {
    "nome": "Thiago Narcizo Dos Santos",
    "cnh": "04548952322",
    "categoria": "D",
    "emissao_cnh": "2009-01-16 00:00:00",
    "validade_cnh": "2032-06-02 00:00:00",
    "situacao": "Aprovar",
    "contrato": "Verificar",
    "data_admissao": "1900-01-01",
    "dataUltimoServicoPrestado": "1900-01-01",
    "telefone": "(21)99734-0085",
    "email": "thiagobeniiiii@gmail.com",
    "sexo": "Masculino",
    "profissao": "Motorista",
    "endereco": "Avenida Presidente Truman 16",
    "complemento": "Bloco 04 Apto 1106",
    "bairro": "Vista Alegre",
    "municipio": "Rio De Janeiro",
    "cep": "24.724-565",
    "banco": "237 – Banco Bradesco S.A.",
    "agencia": "0279",
    "conta": "27778-9",
    "pix": "021997340085",
    "data_nascimento": "1990-10-25 00:00:00",
    "cpf": "142.104.277-05",
    "rg": "27.123.827-1",
    "estado_civil": "Casado(A)",
    "filhos": "2",
    "nome_familiar": "Camila",
    "contato_familiar": "(21)97193-9599",
    "indicado": "N",
    "observacao": "0",
    "arquivos": {
      "cnh_arquivo": [
        "https://www.dropbox.com/scl/fi/s1tca8vmm3e36s02r7lls/1762209815607_Thiago-Narcizo-Dos-Santos-cnh_arquivo.pdf?rlkey=zc58xga7pb7zicix8gq6h708j&dl=0"
      ],
      "comprovante_residencia": [
        "https://www.dropbox.com/scl/fi/th576wj89xocgvjd6nx9g/1762209817493_Thiago-Narcizo-Dos-Santos-comprovante_residencia.pdf?rlkey=3w83lahi6kw4w7u711y40xpm8&dl=0"
      ],
      "curriculo": [
        "https://www.dropbox.com/scl/fi/lwwr658jxwhai5okjcfg3/1762209819005_Thiago-Narcizo-Dos-Santos-curriculo.pdf?rlkey=amfzjdqw6t15529syq7uefrjp&dl=0"
      ],
      "comprovante_mei": [],
      "nada_consta": [
        "https://www.dropbox.com/scl/fi/i9j3kumyerdrfihjmi85s/1762209820494_Thiago-Narcizo-Dos-Santos-nada_consta.pdf?rlkey=5qtirp5uycpjew0pgfoag7ww2&dl=0"
      ]
    },
    "data_envio_utc": "2025-11-03 22:43:43.152000",
    "data_envio_local": "2025-11-03 19:43:43"
  },
  {
    "nome": "Feliphe Da Silva Sant Anna",
    "cnh": "06671547180",
    "categoria": "Ab",
    "emissao_cnh": "2016-09-02 00:00:00",
    "validade_cnh": "2026-03-16 00:00:00",
    "situacao": "Aprovar",
    "contrato": "Verificar",
    "data_admissao": "1900-01-01",
    "dataUltimoServicoPrestado": "1900-01-01",
    "telefone": "(21)97593-9326",
    "email": "feliphe4465@gmail.com",
    "sexo": "Masculino",
    "profissao": "Motorista",
    "endereco": "Rua Matoso Grosso 09",
    "complemento": "Casa",
    "bairro": "Centro",
    "municipio": "Cabo Frio",
    "cep": "28.915-260",
    "banco": "260 – Nu Pagamentos S.A.",
    "agencia": "0001",
    "conta": "494564422",
    "pix": "14656992788",
    "data_nascimento": "1993-11-22 00:00:00",
    "cpf": "146.569.927-98",
    "rg": "24.393.217-5",
    "estado_civil": "Solteiro(A)",
    "filhos": "0",
    "nome_familiar": "Celina",
    "contato_familiar": "(22)98813-4823",
    "indicado": "Mae",
    "observacao": "",
    "arquivos": {
      "cnh_arquivo": [
        "https://www.dropbox.com/scl/fi/pz8bh97d1cehv74uijfb8/1762211899264_Feliphe-Da-Silva-Sant-Anna-cnh_arquivo.png?rlkey=gl84evn5mz4owuuaudkrgfytn&dl=0"
      ],
      "comprovante_residencia": [
        "https://www.dropbox.com/scl/fi/ai9cj3l84l83wrcxp0zhz/1762211900866_Feliphe-Da-Silva-Sant-Anna-comprovante_residencia.pdf?rlkey=60cn97anuzmt7sddpd0kqiiim&dl=0"
      ],
      "curriculo": [
        "https://www.dropbox.com/scl/fi/rm7ojsmgwdzz7wqyri7ao/1762211902508_Feliphe-Da-Silva-Sant-Anna-curriculo.png?rlkey=ahziq6ghvonhbypr4ugqz34wp&dl=0"
      ],
      "comprovante_mei": [],
      "nada_consta": [
        "https://www.dropbox.com/scl/fi/id9td304eb7j7p5ptelaf/1762211903919_Feliphe-Da-Silva-Sant-Anna-nada_consta.pdf?rlkey=xkggpw047vic87l94px9dimf1&dl=0"
      ]
    },
    "data_envio_utc": "2025-11-03 23:18:26.474000",
    "data_envio_local": "2025-11-03 20:18:26"
  }
]